jan883_ollama/__init__.py
jan883_ollama/ollama.py
jan883_ollama-0.1.2.dist-info/METADATA
jan883_ollama-0.1.2.dist-info/WHEEL
jan883_ollama-0.1.2.dist-info/entry_points.txt
jan883_ollama-0.1.2.dist-info/RECORD
