Metadata-Version: 2.4
Name: jan883-ollama
Version: 0.1.2
Summary: Tools to interact with LLM models hosted on Ollama.
Author-email: Jan du Plessis <drjanduplessis@icloud.com>
Requires-Python: >=3.12
Requires-Dist: requests>=2.32.4
